{
  "attachments": [],
  "authorId": "d00ca345-4e31-485c-00e9-0fc880da2dc0",
  "authoredBy": "Damion Young",
  "body": "Staggering",
  "createdOn": 1475151211,
  "forumId": null,
  "indentIndex": 0,
  "lastModified": 1475151211,
  "messageId": 60149,
  "modifiedBy": "d00ca345-4e31-485c-00e9-0fc880da2dc0",
  "readMessages": 1,
  "replies": [],
  "replyTo": null,
  "title": "But wait a second, a second conversation in the first topic",
  "topicId": 148343,
  "totalMessages": 1,
  "deleted": false,
  "draft": false,
  "read": true,
  "entityReference": "\/forums",
  "entityURL": "https:\/\/weblearn.ox.ac.uk\/direct\/forums",
  "entityTitle": "But wait a second, a second conversation in the first topic"
}
